jestor/Client.py
jestor/File.py
jestor/Jestor.py
jestor/Table.py
jestor/User.py
jestor/__init__.py
jestor/test.py
jestor/exception/JestorApiException.py
jestor/exception/__init__.py
jestor/filter/Filter.py
jestor/filter/Operators.py
jestor/filter/__init__.py
jestor-1.0.4.dist-info/LICENSE
jestor-1.0.4.dist-info/METADATA
jestor-1.0.4.dist-info/WHEEL
jestor-1.0.4.dist-info/top_level.txt
jestor-1.0.4.dist-info/RECORD
