Metadata-Version: 2.1
Name: jestor
Version: 1.0.4
Summary: Jestor Python Client
License: MIT License
Project-URL: Homepage, https://github.com/Jestor-Tecnologia/python-client
Project-URL: Bug Tracker, https://github.com/Jestor-Tecnologia/python-client/issues
Classifier: Development Status :: 4 - Beta
Classifier: Programming Language :: Python :: 3
Requires-Python: >=3.7
License-File: LICENSE
